deep_genome/__init__.py
deep_genome/dataset.py
deep_genome/generate.py
deep_genome/model.py
deep_genome/models.py
deep_genome/utils.py
deep_genome-0.1.1.dist-info/LICENSE
deep_genome-0.1.1.dist-info/METADATA
deep_genome-0.1.1.dist-info/WHEEL
deep_genome-0.1.1.dist-info/top_level.txt
deep_genome-0.1.1.dist-info/RECORD
