Metadata-Version: 2.1
Name: deep-genome
Version: 0.1.1
Summary: Synthetic Protein Generation
Home-page: https://github.com/nitinnairk/deep_genome
Author: Nitin Nair
Author-email: nitinnair@vt.edu
License: UNKNOWN
Platform: UNKNOWN
Classifier: Programming Language :: Python :: 3
Classifier: License :: OSI Approved :: GNU General Public License v3 or later (GPLv3+)
Classifier: Operating System :: Unix
Requires-Python: >=3.6
